{
    "pac": {
        "name": "LINCOLN CLUB OF NORTHERN CALIFORNIA FEDERAL PAC",
        "committee_type": "Q",
        "total_receipts": 15540.0,
        "indiv_contrib": 15540.0,
        "total_spent": 1000.0,
        "cash_on_hand": 62863.0
    },
    "stats": {
        "candidates_funded": 1
    },
    "recipients": [
        {
            "cand_id": "H6CA01285",
            "cand_name": "GALLAGHER, JAMES",
            "party": "REP",
            "state": "CA",
            "total_amt": 1000.0,
            "direct_amt": 1000.0,
            "ie_amt": 0.0,
            "bundled_amt": 0.0
        }
    ],
    "pacTransfers": [],
    "cmte_id": "C00148882"
}