{
    "pac": {
        "name": "AMERICAN PRINCIPLES",
        "committee_type": "Q",
        "total_receipts": 50757.0,
        "indiv_contrib": 50167.0,
        "total_spent": 46010.0,
        "cash_on_hand": 61070.0
    },
    "stats": {
        "candidates_funded": 35
    },
    "recipients": [
        {
            "cand_id": "H6FL06258",
            "cand_name": "FINE, RANDY",
            "party": "REP",
            "state": "FL",
            "total_amt": 3000.0,
            "direct_amt": 3000.0,
            "ie_amt": 0.0,
            "bundled_amt": 0.0
        },
        {
            "cand_id": "H6IA02237",
            "cand_name": "MITCHELL, JOE",
            "party": "REP",
            "state": "IA",
            "total_amt": 2250.0,
            "direct_amt": 2250.0,
            "ie_amt": 0.0,
            "bundled_amt": 0.0
        },
        {
            "cand_id": "H8ID01124",
            "cand_name": "FULCHER, RUSSELL",
            "party": "REP",
            "state": "ID",
            "total_amt": 2000.0,
            "direct_amt": 2000.0,
            "ie_amt": 0.0,
            "bundled_amt": 0.0
        },
        {
            "cand_id": "H6FL18097",
            "cand_name": "MAST, BRIAN",
            "party": "REP",
            "state": "FL",
            "total_amt": 2000.0,
            "direct_amt": 2000.0,
            "ie_amt": 0.0,
            "bundled_amt": 0.0
        },
        {
            "cand_id": "H4GA03126",
            "cand_name": "JACK, BRIAN",
            "party": "REP",
            "state": "GA",
            "total_amt": 2000.0,
            "direct_amt": 2000.0,
            "ie_amt": 0.0,
            "bundled_amt": 0.0
        },
        {
            "cand_id": "H0KY06104",
            "cand_name": "BARR, GARLAND ANDY",
            "party": "REP",
            "state": "KY",
            "total_amt": 2000.0,
            "direct_amt": 2000.0,
            "ie_amt": 0.0,
            "bundled_amt": 0.0
        },
        {
            "cand_id": "H4TX26149",
            "cand_name": "GILL, BRANDON",
            "party": "REP",
            "state": "TX",
            "total_amt": 1500.0,
            "direct_amt": 1500.0,
            "ie_amt": 0.0,
            "bundled_amt": 0.0
        },
        {
            "cand_id": "H4MN06087",
            "cand_name": "EMMER, THOMAS EARL JR.",
            "party": "REP",
            "state": "MN",
            "total_amt": 1500.0,
            "direct_amt": 1500.0,
            "ie_amt": 0.0,
            "bundled_amt": 0.0
        },
        {
            "cand_id": "H0NY02234",
            "cand_name": "GARBARINO, ANDREW",
            "party": "REP",
            "state": "NY",
            "total_amt": 1500.0,
            "direct_amt": 1500.0,
            "ie_amt": 0.0,
            "bundled_amt": 0.0
        },
        {
            "cand_id": "H4NY21079",
            "cand_name": "STEFANIK, ELISE M.",
            "party": "REP",
            "state": "NY",
            "total_amt": 1200.0,
            "direct_amt": 1200.0,
            "ie_amt": 0.0,
            "bundled_amt": 0.0
        },
        {
            "cand_id": "S6NC00415",
            "cand_name": "WHATLEY, MICHAEL",
            "party": "REP",
            "state": "NC",
            "total_amt": 1000.0,
            "direct_amt": 1000.0,
            "ie_amt": 0.0,
            "bundled_amt": 0.0
        },
        {
            "cand_id": "S6KY00286",
            "cand_name": "BARR, GARLAND ANDY",
            "party": "REP",
            "state": "KY",
            "total_amt": 1000.0,
            "direct_amt": 1000.0,
            "ie_amt": 0.0,
            "bundled_amt": 0.0
        },
        {
            "cand_id": "S4AZ00188",
            "cand_name": "LAMB, MARK",
            "party": "REP",
            "state": "AZ",
            "total_amt": 1000.0,
            "direct_amt": 1000.0,
            "ie_amt": 0.0,
            "bundled_amt": 0.0
        },
        {
            "cand_id": "H6CT05231",
            "cand_name": "SHEA, CHRIS",
            "party": "REP",
            "state": "CT",
            "total_amt": 1000.0,
            "direct_amt": 1000.0,
            "ie_amt": 0.0,
            "bundled_amt": 0.0
        },
        {
            "cand_id": "H2TN05446",
            "cand_name": "OGLES, ANDY",
            "party": "REP",
            "state": "TN",
            "total_amt": 1000.0,
            "direct_amt": 1000.0,
            "ie_amt": 0.0,
            "bundled_amt": 0.0
        },
        {
            "cand_id": "H2SC07280",
            "cand_name": "FRY, RUSSELL",
            "party": "REP",
            "state": "SC",
            "total_amt": 1000.0,
            "direct_amt": 1000.0,
            "ie_amt": 0.0,
            "bundled_amt": 0.0
        },
        {
            "cand_id": "H0WI07101",
            "cand_name": "TIFFANY, TOM",
            "party": "REP",
            "state": "WI",
            "total_amt": 1000.0,
            "direct_amt": 1000.0,
            "ie_amt": 0.0,
            "bundled_amt": 0.0
        },
        {
            "cand_id": "H0TX13228",
            "cand_name": "JACKSON, RONNY LYNN",
            "party": "REP",
            "state": "TX",
            "total_amt": 1000.0,
            "direct_amt": 1000.0,
            "ie_amt": 0.0,
            "bundled_amt": 0.0
        },
        {
            "cand_id": "H0FL03175",
            "cand_name": "CAMMACK, KAT",
            "party": "REP",
            "state": "FL",
            "total_amt": 1000.0,
            "direct_amt": 1000.0,
            "ie_amt": 0.0,
            "bundled_amt": 0.0
        },
        {
            "cand_id": "H0IN03198",
            "cand_name": "STUTZMAN, MARLIN A",
            "party": "REP",
            "state": "IN",
            "total_amt": 750.0,
            "direct_amt": 750.0,
            "ie_amt": 0.0,
            "bundled_amt": 0.0
        },
        {
            "cand_id": "S8MS00261",
            "cand_name": "HYDE-SMITH, CINDY",
            "party": "REP",
            "state": "MS",
            "total_amt": 500.0,
            "direct_amt": 500.0,
            "ie_amt": 0.0,
            "bundled_amt": 0.0
        },
        {
            "cand_id": "S4IA00129",
            "cand_name": "ERNST, JONI K",
            "party": "REP",
            "state": "IA",
            "total_amt": 500.0,
            "direct_amt": 500.0,
            "ie_amt": 0.0,
            "bundled_amt": 0.0
        },
        {
            "cand_id": "H8TX27049",
            "cand_name": "CLOUD, MICHAEL",
            "party": "REP",
            "state": "TX",
            "total_amt": 500.0,
            "direct_amt": 500.0,
            "ie_amt": 0.0,
            "bundled_amt": 0.0
        },
        {
            "cand_id": "H8SC05158",
            "cand_name": "NORMAN, RALPH W. JR.",
            "party": "REP",
            "state": "SC",
            "total_amt": 500.0,
            "direct_amt": 500.0,
            "ie_amt": 0.0,
            "bundled_amt": 0.0
        },
        {
            "cand_id": "H6KY04171",
            "cand_name": "GALLREIN, ED",
            "party": "REP",
            "state": "KY",
            "total_amt": 500.0,
            "direct_amt": 500.0,
            "ie_amt": 0.0,
            "bundled_amt": 0.0
        },
        {
            "cand_id": "H6FL01390",
            "cand_name": "PATRONIS, JIMMY JR.",
            "party": "REP",
            "state": "FL",
            "total_amt": 500.0,
            "direct_amt": 500.0,
            "ie_amt": 0.0,
            "bundled_amt": 0.0
        },
        {
            "cand_id": "H4WI06048",
            "cand_name": "GROTHMAN, GLENN S.",
            "party": "REP",
            "state": "WI",
            "total_amt": 500.0,
            "direct_amt": 500.0,
            "ie_amt": 0.0,
            "bundled_amt": 0.0
        },
        {
            "cand_id": "H4AZ08108",
            "cand_name": "HAMADEH, ABRAHAM",
            "party": "REP",
            "state": "AZ",
            "total_amt": 500.0,
            "direct_amt": 500.0,
            "ie_amt": 0.0,
            "bundled_amt": 0.0
        },
        {
            "cand_id": "H2PA04135",
            "cand_name": "PERRY, SCOTT",
            "party": "REP",
            "state": "PA",
            "total_amt": 500.0,
            "direct_amt": 500.0,
            "ie_amt": 0.0,
            "bundled_amt": 0.0
        },
        {
            "cand_id": "H2OH15228",
            "cand_name": "CAREY, MIKE",
            "party": "REP",
            "state": "OH",
            "total_amt": 500.0,
            "direct_amt": 500.0,
            "ie_amt": 0.0,
            "bundled_amt": 0.0
        },
        {
            "cand_id": "H2NY17162",
            "cand_name": "LAWLER, MICHAEL VINCENT",
            "party": "REP",
            "state": "NY",
            "total_amt": 500.0,
            "direct_amt": 500.0,
            "ie_amt": 0.0,
            "bundled_amt": 0.0
        },
        {
            "cand_id": "H0GA09246",
            "cand_name": "CLYDE, ANDREW",
            "party": "REP",
            "state": "GA",
            "total_amt": 500.0,
            "direct_amt": 500.0,
            "ie_amt": 0.0,
            "bundled_amt": 0.0
        },
        {
            "cand_id": "H6MS01131",
            "cand_name": "KELLY, JOHN TRENT",
            "party": "REP",
            "state": "MS",
            "total_amt": 300.0,
            "direct_amt": 300.0,
            "ie_amt": 0.0,
            "bundled_amt": 0.0
        },
        {
            "cand_id": "H4IN03174",
            "cand_name": "STUTZMAN FOR CONGRESS",
            "party": null,
            "state": null,
            "total_amt": 300.0,
            "direct_amt": 300.0,
            "ie_amt": 0.0,
            "bundled_amt": 0.0
        },
        {
            "cand_id": "S0AL00230",
            "cand_name": "TUBERVILLE, THOMAS H",
            "party": "REP",
            "state": "AL",
            "total_amt": 0.0,
            "direct_amt": 0.0,
            "ie_amt": 0.0,
            "bundled_amt": 0.0
        }
    ],
    "pacTransfers": [
        {
            "cmte_id": "C00561183",
            "pac_name": "TENNEY FOR CONGRESS",
            "total_amt": 500.0,
            "tx_count": 1
        },
        {
            "cmte_id": "C00649236",
            "pac_name": "MARK HARRIS FOR CONGRESS",
            "total_amt": 500.0,
            "tx_count": 1
        },
        {
            "cmte_id": "C00565846",
            "pac_name": "IOWA VALUES",
            "total_amt": 120.0,
            "tx_count": 1
        }
    ],
    "cmte_id": "C00492579"
}