{
    "pac": {
        "name": "TEAM MACE",
        "committee_type": "N",
        "total_receipts": 587243.0,
        "indiv_contrib": 586310.0,
        "total_spent": 589377.0,
        "cash_on_hand": 3467.0
    },
    "stats": {
        "candidates_funded": 0
    },
    "recipients": [],
    "pacTransfers": [
        {
            "cmte_id": "C00763326",
            "pac_name": "MUST ACT TO CREATE EXCELLENCE PAC",
            "total_amt": 8133.0,
            "tx_count": 2
        }
    ],
    "cmte_id": "C00768838"
}