{
    "politician": {
        "cand_name": "GALLAGHER, JAMES",
        "party": "REP",
        "state": "CA",
        "indiv_total": 540351.0,
        "pac_receipts_summary": 126740.0
    },
    "donations": [
        {
            "cmte_id": "C00024422",
            "pac_name": "SUPPORTERS OF OPERATING ENGINEERS LOCAL UNION #3 ENDORSED CANDIDATES",
            "total_amt": 5000.0,
            "direct_amt": 5000.0,
            "ie_amt": 0.0
        },
        {
            "cmte_id": "C00197715",
            "pac_name": "AMERICAN PISTACHIO GROWERS PISTACHIO POLITICAL ACTION COMMITTEE",
            "total_amt": 5000.0,
            "direct_amt": 5000.0,
            "ie_amt": 0.0
        },
        {
            "cmte_id": "C00349746",
            "pac_name": "CALIFORNIA DAIRIES, INC. FEDERAL POLITICAL ACTION COMMITTEE",
            "total_amt": 5000.0,
            "direct_amt": 5000.0,
            "ie_amt": 0.0
        },
        {
            "cmte_id": "C00390161",
            "pac_name": "EUREKA POLITICAL ACTION COMMITTEE",
            "total_amt": 5000.0,
            "direct_amt": 5000.0,
            "ie_amt": 0.0
        },
        {
            "cmte_id": "C00428052",
            "pac_name": "MAJORITY COMMITTEE PAC--MC PAC",
            "total_amt": 5000.0,
            "direct_amt": 5000.0,
            "ie_amt": 0.0
        },
        {
            "cmte_id": "C00467431",
            "pac_name": "THE EYE OF THE TIGER POLITICAL ACTION COMMITTEE",
            "total_amt": 5000.0,
            "direct_amt": 5000.0,
            "ie_amt": 0.0
        },
        {
            "cmte_id": "C00526715",
            "pac_name": "GREATER TOMORROW POLITICAL ACTION COMMITTEE",
            "total_amt": 5000.0,
            "direct_amt": 5000.0,
            "ie_amt": 0.0
        },
        {
            "cmte_id": "C00563726",
            "pac_name": "MR. SOUTHERN MISSOURIAN IN THE HOUSE PAC",
            "total_amt": 5000.0,
            "direct_amt": 5000.0,
            "ie_amt": 0.0
        },
        {
            "cmte_id": "C00639229",
            "pac_name": "AMERICAN REVIVAL PAC",
            "total_amt": 5000.0,
            "direct_amt": 5000.0,
            "ie_amt": 0.0
        },
        {
            "cmte_id": "C00693796",
            "pac_name": "BUCKEYE LIBERTY POLITICAL ACTION COMMITTEE",
            "total_amt": 5000.0,
            "direct_amt": 5000.0,
            "ie_amt": 0.0
        },
        {
            "cmte_id": "C00882571",
            "pac_name": "STATE BUILDING & CONSTRUCTION TRADES COUNCIL OF CALIFORNIA FEDERAL PAC",
            "total_amt": 5000.0,
            "direct_amt": 5000.0,
            "ie_amt": 0.0
        },
        {
            "cmte_id": "C00027342",
            "pac_name": "INTERNATIONAL BROTHERHOOD OF ELECTRICAL WORKERS POLITICAL ACTION COMMITTEE",
            "total_amt": 3500.0,
            "direct_amt": 3500.0,
            "ie_amt": 0.0
        },
        {
            "cmte_id": "C00308478",
            "pac_name": "USA RICE FEDERATION PAC",
            "total_amt": 3500.0,
            "direct_amt": 3500.0,
            "ie_amt": 0.0
        },
        {
            "cmte_id": "C00362624",
            "pac_name": "CALIFORNIA RICE INDUSTRY ASSOCIATION FUND (CALIFORNIA RICE FUND)",
            "total_amt": 3500.0,
            "direct_amt": 3500.0,
            "ie_amt": 0.0
        },
        {
            "cmte_id": "C00000901",
            "pac_name": "BUILD POLITICAL ACTION COMMITTEE OF THE NATIONAL ASSOCIATION OF HOME BUILDERS (BUILDPAC)",
            "total_amt": 2500.0,
            "direct_amt": 2500.0,
            "ie_amt": 0.0
        },
        {
            "cmte_id": "C00264770",
            "pac_name": "AGRICULTURAL RETAILERS ASSOCIATION POLITICAL ACTION COMMITTE",
            "total_amt": 2500.0,
            "direct_amt": 2500.0,
            "ie_amt": 0.0
        },
        {
            "cmte_id": "C00318766",
            "pac_name": "CALIFORNIA INDEPENDENT PETROLEUM ASSOCIATION FEDERAL PAC",
            "total_amt": 2500.0,
            "direct_amt": 2500.0,
            "ie_amt": 0.0
        },
        {
            "cmte_id": "C00683508",
            "pac_name": "FOREVER YOUTH ORGANIZATION UTILIZING A NEW GENERATION PAC",
            "total_amt": 2500.0,
            "direct_amt": 2500.0,
            "ie_amt": 0.0
        },
        {
            "cmte_id": "C00416594",
            "pac_name": "THE GALLAGHER COMMITTEE",
            "total_amt": 2000.0,
            "direct_amt": 2000.0,
            "ie_amt": 0.0
        },
        {
            "cmte_id": "C00518787",
            "pac_name": "CALIFORNIA CATTLEMEN'S ASSOCIATION FEDERAL PAC",
            "total_amt": 2000.0,
            "direct_amt": 2000.0,
            "ie_amt": 0.0
        },
        {
            "cmte_id": "C00608695",
            "pac_name": "GALLAGHER FOR CONGRESS",
            "total_amt": 2000.0,
            "direct_amt": 2000.0,
            "ie_amt": 0.0
        },
        {
            "cmte_id": "C00935114",
            "pac_name": "SECRETARY OF STATE",
            "total_amt": 1740.0,
            "direct_amt": 1740.0,
            "ie_amt": 0.0
        },
        {
            "cmte_id": "C00942458",
            "pac_name": "GALLAGHER FOR CONGRESS",
            "total_amt": 1740.0,
            "direct_amt": 0.0,
            "ie_amt": 0.0
        },
        {
            "cmte_id": "C00523381",
            "pac_name": "HEARTDOCPAC",
            "total_amt": 1500.0,
            "direct_amt": 1500.0,
            "ie_amt": 0.0
        },
        {
            "cmte_id": "C00146605",
            "pac_name": "FARMERS' RICE COOPERATIVE FUND",
            "total_amt": 1000.0,
            "direct_amt": 1000.0,
            "ie_amt": 0.0
        },
        {
            "cmte_id": "C00148882",
            "pac_name": "LINCOLN CLUB OF NORTHERN CALIFORNIA FEDERAL PAC",
            "total_amt": 1000.0,
            "direct_amt": 1000.0,
            "ie_amt": 0.0
        },
        {
            "cmte_id": "C00473272",
            "pac_name": "GALLAGHER FOR CONGRESS",
            "total_amt": 1000.0,
            "direct_amt": 1000.0,
            "ie_amt": 0.0
        },
        {
            "cmte_id": "C00627992",
            "pac_name": "ALMOND ALLIANCE PAC FEDERAL",
            "total_amt": 1000.0,
            "direct_amt": 1000.0,
            "ie_amt": 0.0
        }
    ],
    "indivStats": {
        "unique_donors": 439,
        "oos_donors": 35,
        "oos_total": 45860.0
    },
    "opposition": []
}